mastercardqkr/__init__.py
mastercardqkr/beneficiary.py
mastercardqkr/beneficiarycustomfield.py
mastercardqkr/card.py
mastercardqkr/cart.py
mastercardqkr/cartitem.py
mastercardqkr/cartvalidation.py
mastercardqkr/country.py
mastercardqkr/creditnote.py
mastercardqkr/externaltrans.py
mastercardqkr/forgottenpassword.py
mastercardqkr/form.py
mastercardqkr/formsubmission.py
mastercardqkr/inboxmessage.py
mastercardqkr/lightbox.py
mastercardqkr/menu.py
mastercardqkr/merchant.py
mastercardqkr/order.py
mastercardqkr/orderahead.py
mastercardqkr/orderaheadmenu.py
mastercardqkr/ordercalendar.py
mastercardqkr/orderslot.py
mastercardqkr/ordertotal.py
mastercardqkr/posorder.py
mastercardqkr/pospaymentnotification.py
mastercardqkr/prodgroup.py
mastercardqkr/refund.py
mastercardqkr/resendotp.py
mastercardqkr/resourceconfig.py
mastercardqkr/securityquestion.py
mastercardqkr/trans.py
mastercardqkr/updatepassword.py
mastercardqkr/user.py
mastercardqkr/userimage.py
mastercardqkr/usersession.py
mastercardqkr/verifyotp.py
mastercard_qkr-1.3.0.dist-info/LICENSE
mastercard_qkr-1.3.0.dist-info/METADATA
mastercard_qkr-1.3.0.dist-info/WHEEL
mastercard_qkr-1.3.0.dist-info/top_level.txt
mastercard_qkr-1.3.0.dist-info/RECORD
