Metadata-Version: 2.1
Name: mastercard-qkr
Version: 1.3.0
Summary: This is the Mastercard qkr SDK
Home-page: https://developer.mastercard.com
Author: Mastercard
Author-email: UNKNOWN
License: BSD
Platform: UNKNOWN
Classifier: Intended Audience :: Developers
Classifier: Natural Language :: English
Classifier: Operating System :: OS Independent
Classifier: Programming Language :: Python :: 2.7
Classifier: Programming Language :: Python :: 3.5
Classifier: Programming Language :: Python :: 3.6
Classifier: Topic :: Software Development :: Libraries :: Python Modules
Requires-Dist: mastercard-api-core (<1.5.0,>=1.4.0)
